setup.py
bg11_distributions/Binomialdistribution.py
bg11_distributions/Gaussiandistribution.py
bg11_distributions/Generaldistribution.py
bg11_distributions/__init__.py
bg11_distributions.egg-info/PKG-INFO
bg11_distributions.egg-info/SOURCES.txt
bg11_distributions.egg-info/dependency_links.txt
bg11_distributions.egg-info/not-zip-safe
bg11_distributions.egg-info/top_level.txt